chess_bead/__init__.py
chess_bead/cwfs.ttf
chess_bead/example.pgn
chess_bead/poems.json
chess_bead-1.0.2.dist-info/LICENSE
chess_bead-1.0.2.dist-info/WHEEL
chess_bead-1.0.2.dist-info/METADATA
chess_bead-1.0.2.dist-info/RECORD
