Metadata-Version: 2.1
Name: chess_bead
Version: 1.0.2
Summary: Package for the both Chinese poetry and chess game. The rules of the game
Home-page: https://github.com/nevmenandr/chess_bead
Author: Boris Orekhov
Author-email: nevmenandr@gmail.com
Requires-Python: >=3.5
Classifier: License :: OSI Approved :: GNU General Public License v3 or later (GPLv3+)
Classifier: Programming Language :: Python :: 3
Classifier: Natural Language :: Chinese (Traditional)
Requires-Dist: chess >=1.6.1
Requires-Dist: pillow>=7.0.0
Requires-Dist: imageio>=1.18.5
